nox_py_sdk/__init__.py
nox_py_sdk/api_types.py
nox_py_sdk/checkout_api.py
nox_py_sdk/v2_api.py
tests/__init__.py
tests/test_checkout_api.py
nox_py_sdk-0.1.0.dist-info/METADATA
nox_py_sdk-0.1.0.dist-info/WHEEL
nox_py_sdk-0.1.0.dist-info/top_level.txt
nox_py_sdk-0.1.0.dist-info/RECORD
