Metadata-Version: 2.1
Name: nox-py-sdk
Version: 0.1.0
Summary: An SDK made with Python to interact with the Checkout API and V2 API in a simple and efficient way.
Author: Rafael Faria
Author-email: rafael@capyba.com
Classifier: Programming Language :: Python :: 3
Classifier: Operating System :: OS Independent
Requires-Python: >=3.6
Requires-Dist: requests>=2.25.1
